amplitude_data_wrapper/__init__.py
amplitude_data_wrapper/analytics_api.py
amplitude_data_wrapper-0.5.8.dist-info/licenses/LICENSE
amplitude_data_wrapper-0.5.8.dist-info/METADATA
amplitude_data_wrapper-0.5.8.dist-info/WHEEL
amplitude_data_wrapper-0.5.8.dist-info/top_level.txt
amplitude_data_wrapper-0.5.8.dist-info/RECORD
