Metadata-Version: 2.4
Name: amplitude-data-wrapper
Version: 0.5.8
Summary: python wrapper for using the amplitude analytics and taxonomy APIs
Author-email: Tobias McVey <tobias.mcvey@nav.no>
License-Expression: MIT
Project-URL: Homepage, https://github.com/navikt/amplitude-data-wrapper
Keywords: amplitude
Requires-Python: >=3.10
License-File: LICENSE
Requires-Dist: requests>=2.32.3
Requires-Dist: tqdm>=4.67.1
Dynamic: license-file
